odoo/addons/model_access_restriction/README.rst
odoo/addons/model_access_restriction/__init__.py
odoo/addons/model_access_restriction/__manifest__.py
odoo/addons/model_access_restriction/i18n/es.po
odoo/addons/model_access_restriction/models/__init__.py
odoo/addons/model_access_restriction/models/ir_model_access_restriction.py
odoo/addons/model_access_restriction/models/models.py
odoo/addons/model_access_restriction/readme/CONFIGURE.md
odoo/addons/model_access_restriction/readme/CONTRIBUTORS.md
odoo/addons/model_access_restriction/readme/DESCRIPTION.md
odoo/addons/model_access_restriction/security/ir.model.access.csv
odoo/addons/model_access_restriction/static/description/icon.png
odoo/addons/model_access_restriction/static/description/icon.svg
odoo/addons/model_access_restriction/static/description/index.html
odoo/addons/model_access_restriction/tests/__init__.py
odoo/addons/model_access_restriction/tests/test_model_access_restriction.py
odoo/addons/model_access_restriction/views/ir_model_access_restriction_views.xml
odoo_addon_model_access_restriction-16.0.1.0.0.1.dist-info/METADATA
odoo_addon_model_access_restriction-16.0.1.0.0.1.dist-info/WHEEL
odoo_addon_model_access_restriction-16.0.1.0.0.1.dist-info/top_level.txt
odoo_addon_model_access_restriction-16.0.1.0.0.1.dist-info/RECORD
