Metadata-Version: 2.1
Name: odoo-addon-model_access_restriction
Version: 16.0.1.0.0.1
Summary: New type of access rule to restrict permissions based on groups
Home-page: https://github.com/sygel-technology/sy-server-backend
Author: Sygel, Odoo Community Association (OCA)
Author-email: support@odoo-community.org
License: AGPL-3
Classifier: Programming Language :: Python
Classifier: Framework :: Odoo
Classifier: Framework :: Odoo :: 16.0
Classifier: License :: OSI Approved :: GNU Affero General Public License v3
Requires-Python: >=3.10
Requires-Dist: odoo<16.1dev,>=16.0a
